kNNp/__init__.py
kNNp/p_system.py
kNNp-0.0.1.dist-info/LICENSE
kNNp-0.0.1.dist-info/METADATA
kNNp-0.0.1.dist-info/WHEEL
kNNp-0.0.1.dist-info/top_level.txt
kNNp-0.0.1.dist-info/RECORD
