Metadata-Version: 2.1
Name: kNNp
Version: 0.0.1
Summary: A kNN classifier optimized by P systems
Author: Khushiyant
Author-email: <khushiyant2002@gmail.com>
Keywords: knn,theoretical computer science,machine learning,p systems
Classifier: Intended Audience :: Developers
Classifier: Programming Language :: Python :: 3
Classifier: Operating System :: Unix
Classifier: Operating System :: MacOS :: MacOS X
Classifier: Operating System :: Microsoft :: Windows
License-File: LICENSE
Requires-Dist: numpy
